data/__init__.py
data/DAO/GenericDAO.py
data/DAO/GenericDAOImp.py
data/DAO/__init__.py
data/conn/DatabaseConnection.py
data/conn/DatabaseCursor.py
data/conn/Psycopg2Connection.py
data/conn/Psycopg2Cursor.py
data/conn/__init__.py
db_dao-1.3.0.dist-info/METADATA
db_dao-1.3.0.dist-info/WHEEL
db_dao-1.3.0.dist-info/top_level.txt
db_dao-1.3.0.dist-info/RECORD
