Metadata-Version: 2.1
Name: db-dao
Version: 1.3.0
Author: Gustavo Gomes Dias
Author-email: gustavo.dias@cedisa.com.br
